modes/__init__.py
modes/_analyse.py
modes/_mode_solver.py
modes/_mode_solver_full_vectorial.py
modes/_mode_solver_lib.py
modes/_mode_solver_semi_vectorial.py
modes/_structure.py
modes/_structure_base.py
modes/autoname.py
modes/config.py
modes/coupling_efficiency.py
modes/design.py
modes/get_modes_jsonpath.py
modes/group_index.py
modes/materials.py
modes/mode_solver_full.py
modes/mode_solver_semi.py
modes/neff.py
modes/sweep_waveguide.py
modes/sweep_wavelength.py
modes/types.py
modes/waveguide.py
modes-1.0.6.dist-info/LICENSE
modes-1.0.6.dist-info/METADATA
modes-1.0.6.dist-info/WHEEL
modes-1.0.6.dist-info/top_level.txt
modes-1.0.6.dist-info/RECORD
