Metadata-Version: 2.1
Name: modes
Version: 1.0.6
Summary: Photonic mode solver.
Home-page: https://modes.readthedocs.io/en/latest/
Author: Jean-Luc Tambasco
Author-email: an.obscurity@gmail.com
License: MIT
Platform: UNKNOWN
Requires-Python: >=3.8
License-File: LICENSE
